README.rst
setup.cfg
setup.py
src/docutils_shell/__init__.py
src/docutils_shell/docutils_shell.py
src/docutils_shell.egg-info/PKG-INFO
src/docutils_shell.egg-info/SOURCES.txt
src/docutils_shell.egg-info/dependency_links.txt
src/docutils_shell.egg-info/requires.txt
src/docutils_shell.egg-info/top_level.txt