Metadata-Version: 1.1
Name: docutils-shell
Version: 0.0.2
Summary: docutils extension to insert stdout of given shell command
Home-page: https://bitbucket.org/pwexler/docutils_shell
Author: Paul Wexler
Author-email: paul@prometheusresearch.com
License: MIT
Keywords: docutils,sphinx,shell,documentation
Platform: Any
Classifier: Programming Language :: Python
Classifier: Intended Audience :: Developers
